aifn/__init__.py
aifn/client.py
aifn/constants.py
aifn/function.py
aifn/utils.py
aifn-0.2.2.dist-info/LICENSE
aifn-0.2.2.dist-info/METADATA
aifn-0.2.2.dist-info/WHEEL
aifn-0.2.2.dist-info/top_level.txt
aifn-0.2.2.dist-info/RECORD
