Metadata-Version: 2.1
Name: aifn
Version: 0.2.2
Summary: Documentation for `aifn`, a client facing API for interacting with the WecoAI's AI functions.
Author-email: Weco AI Team <dhruv@weco.ai>
License: MIT
Project-URL: Homepage, https://github.com/WecoAI/aifn-python
Keywords: AI,LLM,VLM,AI functions,Prompt Engineering,NLP
Classifier: Programming Language :: Python :: 3
Classifier: Operating System :: OS Independent
Classifier: License :: OSI Approved :: MIT License
Requires-Python: >=3.8
License-File: LICENSE
Requires-Dist: requests
Requires-Dist: asyncio
Requires-Dist: nest_asyncio
Requires-Dist: httpx[http2]
Requires-Dist: pillow
Provides-Extra: dev
Requires-Dist: ruff; extra == "dev"
Requires-Dist: pytest-asyncio; extra == "dev"
Requires-Dist: pytest-xdist; extra == "dev"
Requires-Dist: build; extra == "dev"
Requires-Dist: setuptools_scm; extra == "dev"
Provides-Extra: docs
Requires-Dist: jupyter; extra == "docs"
Requires-Dist: black; extra == "docs"
Requires-Dist: mkdocs; extra == "docs"
Requires-Dist: mkdocs-material; extra == "docs"
Requires-Dist: mkdocs-material-extensions; extra == "docs"
Requires-Dist: mkdocstrings[crystal,python]; extra == "docs"
Requires-Dist: mkdocs-minify-plugin; extra == "docs"
